pipg/__init__.py
pipg/cli.py
pipg/package_manager.py
pipg/requirements_manager.py
pipg/utils.py
pipg-0.3.1.dist-info/METADATA
pipg-0.3.1.dist-info/WHEEL
pipg-0.3.1.dist-info/entry_points.txt
pipg-0.3.1.dist-info/top_level.txt
pipg-0.3.1.dist-info/RECORD
