Metadata-Version: 2.2
Name: pipg
Version: 0.3.1
Summary: Wrapper para pip que automatiza a instalação, remoção e gerenciamento de dependências em arquivos de requirements.
Home-page: https://github.com/GuilhermeGonSoares/pipg
Author: Guilherme Gonçalves Soares
Author-email: guilherme16.gon@gmail.com
Classifier: Programming Language :: Python :: 3
Classifier: License :: OSI Approved :: MIT License
Classifier: Operating System :: OS Independent
Requires-Python: >=3.6
Dynamic: author
Dynamic: author-email
Dynamic: classifier
Dynamic: description
Dynamic: description-content-type
Dynamic: home-page
Dynamic: requires-python
Dynamic: summary
